LICENSE
MANIFEST.in
Makefile
README.rst
setup.py
pycukes.egg-info/PKG-INFO
pycukes.egg-info/SOURCES.txt
pycukes.egg-info/dependency_links.txt
pycukes.egg-info/entry_points.txt
pycukes.egg-info/not-zip-safe
pycukes.egg-info/requires.txt
pycukes.egg-info/top_level.txt
specs/__init__.py
specs/finding_hooks.py
specs/finding_steps_in_directory.py
specs/finding_text_specs_and_steps_modules.py
specs/finding_text_specs_in_a_dir.py
specs/module_with_no_step_definition.py
specs/no_scenario_story.py
specs/run_specs.py
specs/running_after_snippets.py
specs/running_before_snippets.py
specs/single_ok_scenario.py
specs/single_pending_scenario.py
specs/single_scenario_with_one_ok_one_failure_and_one_error.py
specs/single_scenario_with_two_oks_and_one_failure.py
specs/two_scenarios_each_one_with_two_oks_and_a_fail.py
specs/unit_spec_for_find_steps_method.py
specs/using_regexes_in_steps_definitions.py
specs/steps/__init__.py
specs/steps/bowling_game_steps.py
specs/steps/calculator_with_regexes.py
specs/steps/sum_of_one_and_two_negative_with_two_oks_and_one_fail.py
specs/steps/sum_of_one_and_two_with_one_fail_and_two_oks.py
specs/steps/sum_of_one_and_two_with_one_ok_one_fail_and_one_error.py
specs/steps/sum_of_one_and_two_with_three_oks.py
src/__init__.py
src/console.py
src/finder.py
src/hooks.py
src/runner.py