Metadata-Version: 1.0
Name: pycukes
Version: 0.2
Summary: A Cucumber-like BDD framework built on top of Pyhistorian
Home-page: http://github.com/hugobr/pycukes
Author: Hugo Lopes Tavares
Author-email: hltbra@gmail.com
License: MIT License
Keywords: bdd behaviour behavior pyhistorian story
Platform: UNKNOWN
Classifier: Development Status :: 4 - Beta
Classifier: Environment :: Console
Classifier: Intended Audience :: Developers
Classifier: License :: OSI Approved :: MIT License
Classifier: Programming Language :: Python
Classifier: Topic :: Software Development :: Documentation
Classifier: Topic :: Software Development :: Testing
